newlines/__init__.py
newlines/new_lines.py
newlines-1.0.0.dist-info/METADATA
newlines-1.0.0.dist-info/WHEEL
newlines-1.0.0.dist-info/top_level.txt
newlines-1.0.0.dist-info/RECORD
