Metadata-Version: 2.4
Name: newlines
Version: 1.0.0
Summary: printを%nl%で改行
License: MIT
Requires-Python: >=3.7
Dynamic: license
Dynamic: requires-python
Dynamic: summary
